[
  {
    "title": "目前🌆摩登都市🌆伺服器還在整修中！",
    "content": "請所有玩家，市民不要入城感謝配合!",
    "time": "2025-11-17 02:00",
    "color": "#FF9D4C"
  },
  {
    "title": "目前🌆摩登都市🌆伺服器還在整修中！",
    "content": "請所有玩家，市民不要入城感謝配合!",
    "time": "2025-11-17 02:00",
    "color": "#FF9D4C"
  },
  {
    "title": "目前🌆摩登都市🌆伺服器還在整修中！",
    "content": "請所有玩家，市民不要入城感謝配合!",
    "time": "2025-11-17 02:00",
    "color": "#FF9D4C"
},
{
    "title": "目前🌆摩登都市🌆伺服器還在整修中！",
    "content": "請所有玩家，市民不要入城感謝配合!",
    "time": "2025-11-17 02:00",
    "color": "#FF9D4C"
}
]
